Workbook

Sheet Financial Data
A1: Company | B1: Year | C1: Revenue (Cr) | D1: Net Profit (Cr) | E1: Operating Margin | F1: Equity Capital (Cr) | G1: Reserves (Cr) | H1: Total Equity (Cr) | I1: Borrowings (Cr) | J1: Debt to Equity | K1: ROE | L1: ROCE | M1: EPS (Rs) | N1: YoY Revenue Growth | O1: Net Margin | P1: Avg USD/INR (FY) | Q1: Revenue (USD Mn, approx) | R1: YoY USD Revenue Growth
A2: TCS | B2: FY2021 | C2: 164177 | D2: 32562 | E2: 0.28 | F2: 370 | G2: 86063 | H2: =F2+G2 -> 86433 | I2: 7795 | J2: =I2/H2 -> 0.090185462 | K2: =D2/H2 -> 0.37673111 | L2: 0.47 | M2: 87.67 | N2: - | O2: =D2/C2 -> 0.19833472 | P2: 74.2 | Q2: =C2*10/P2 -> 22126.28 | R2: -
A3: TCS | B3: FY2022 | C3: 191754 | D3: 38449 | E3: 0.28 | F3: 366 | G3: 88773 | H3: =F3+G3 -> 89139 | I3: 7818 | J3: =I3/H3 -> 0.087705718 | K3: =D3/H3 -> 0.43133757 | L3: 0.49 | M3: 104.75 | N3: =(C3-C2)/C2 -> 0.16797115 | O3: =D3/C3 -> 0.20051211 | P3: 74.5 | Q3: =C3*10/P3 -> 25738.792 | R3: =(Q3-Q2)/Q2 -> 0.16326791
A4: TCS | B4: FY2023 | C4: 225458 | D4: 42303 | E4: 0.26 | F4: 366 | G4: 90058 | H4: =F4+G4 -> 90424 | I4: 7688 | J4: =I4/H4 -> 0.085021676 | K4: =D4/H4 -> 0.46782934 | L4: 0.54 | M4: 115.19 | N4: =(C4-C3)/C3 -> 0.17576687 | O4: =D4/C4 -> 0.1876314 | P4: 80.4 | Q4: =C4*10/P4 -> 28042.04 | R4: =(Q4-Q3)/Q3 -> 0.089485468
A5: TCS | B5: FY2024 | C5: 240893 | D5: 46099 | E5: 0.27 | F5: 362 | G5: 90127 | H5: =F5+G5 -> 90489 | I5: 8021 | J5: =I5/H5 -> 0.088640608 | K5: =D5/H5 -> 0.50944314 | L5: 0.59 | M5: 126.88 | N5: =(C5-C4)/C4 -> 0.068460645 | O5: =D5/C5 -> 0.19136712 | P5: 82.8 | Q5: =C5*10/P5 -> 29093.357 | R5: =(Q5-Q4)/Q4 -> 0.037490771
A6: TCS | B6: FY2025 | C6: 255324 | D6: 48797 | E6: 0.26 | F6: 362 | G6: 94394 | H6: =F6+G6 -> 94756 | I6: 9392 | J6: =I6/H6 -> 0.099117734 | K6: =D6/H6 -> 0.5149753 | L6: 0.64 | M6: 134.2 | N6: =(C6-C5)/C5 -> 0.059906265 | O6: =D6/C6 -> 0.19111795 | P6: 84.5 | Q6: =C6*10/P6 -> 30215.858 | R6: =(Q6-Q5)/Q5 -> 0.038582707
A7: Infosys | B7: FY2021 | C7: 100472 | D7: 19423 | E7: 0.28 | F7: 2124 | G7: 74227 | H7: =F7+G7 -> 76351 | I7: 5325 | J7: =I7/H7 -> 0.069743684 | K7: =D7/H7 -> 0.25439091 | L7: 0.32 | M7: 45.42 | N7: - | O7: =D7/C7 -> 0.19331754 | P7: 74.2 | Q7: =C7*10/P7 -> 13540.701 | R7: -
A8: Infosys | B8: FY2022 | C8: 121641 | D8: 22146 | E8: 0.26 | F8: 2098 | G8: 73252 | H8: =F8+G8 -> 75350 | I8: 5474 | J8: =I8/H8 -> 0.072647644 | K8: =D8/H8 -> 0.29390843 | L8: 0.35 | M8: 52.56 | N8: =(C8-C7)/C7 -> 0.21069552 | O8: =D8/C8 -> 0.18206033 | P8: 74.5 | Q8: =C8*10/P8 -> 16327.651 | R8: =(Q8-Q7)/Q7 -> 0.20582023
A9: Infosys | B9: FY2023 | C9: 146767 | D9: 24108 | E9: 0.24 | F9: 2069 | G9: 73338 | H9: =F9+G9 -> 75407 | I9: 8299 | J9: =I9/H9 -> 0.1100561 | K9: =D9/H9 -> 0.31970507 | L9: 0.37 | M9: 58.08 | N9: =(C9-C8)/C8 -> 0.20655864 | O9: =D9/C9 -> 0.16426036 | P9: 80.4 | Q9: =C9*10/P9 -> 18254.602 | R9: =(Q9-Q8)/Q8 -> 0.11801765
A10: Infosys | B10: FY2024 | C10: 153670 | D10: 26248 | E10: 0.24 | F10: 2071 | G10: 86045 | H10: =F10+G10 -> 88116 | I10: 8359 | J10: =I10/H10 -> 0.094863589 | K10: =D10/H10 -> 0.29788007 | L10: 0.4 | M10: 63.2 | N10: =(C10-C9)/C9 -> 0.047033734 | O10: =D10/C10 -> 0.17080757 | P10: 82.8 | Q10: =C10*10/P10 -> 18559.179 | R10: =(Q10-Q9)/Q9 -> 0.01668493
A11: Infosys | B11: FY2025 | C11: 162990 | D11: 26750 | E11: 0.24 | F11: 2073 | G11: 93745 | H11: =F11+G11 -> 95818 | I11: 8227 | J11: =I11/H11 -> 0.085860694 | K11: =D11/H11 -> 0.2791751 | L11: 0.4 | M11: 64.32 | N11: =(C11-C10)/C10 -> 0.060649444 | O11: =D11/C11 -> 0.1641205 | P11: 84.5 | Q11: =C11*10/P11 -> 19288.757 | R11: =(Q11-Q10)/Q10 -> 0.039310934
A12: Wipro | B12: FY2021 | C12: 61935 | D12: 10868 | E12: 0.24 | F12: 1096 | G12: 53805 | H12: =F12+G12 -> 54901 | I12: 10451 | J12: =I12/H12 -> 0.19036083 | K12: =D12/H12 -> 0.19795632 | L12: 0.2 | M12: 9.85 | N12: - | O12: =D12/C12 -> 0.17547429 | P12: 74.2 | Q12: =C12*10/P12 -> 8347.035 | R12: -
A13: Wipro | B13: FY2022 | C13: 79312 | D13: 12243 | E13: 0.21 | F13: 1096 | G13: 64307 | H13: =F13+G13 -> 65403 | I13: 17593 | J13: =I13/H13 -> 0.26899378 | K13: =D13/H13 -> 0.18719325 | L13: 0.22 | M13: 11.15 | N13: =(C13-C12)/C12 -> 0.28056834 | O13: =D13/C13 -> 0.15436504 | P13: 74.5 | Q13: =C13*10/P13 -> 10645.906 | R13: =(Q13-Q12)/Q12 -> 0.27541169
A14: Wipro | B14: FY2023 | C14: 90488 | D14: 11366 | E14: 0.19 | F14: 1098 | G14: 76570 | H14: =F14+G14 -> 77668 | I14: 17467 | J14: =I14/H14 -> 0.22489313 | K14: =D14/H14 -> 0.14634084 | L14: 0.21 | M14: 10.34 | N14: =(C14-C13)/C13 -> 0.14091184 | O14: =D14/C14 -> 0.12560782 | P14: 80.4 | Q14: =C14*10/P14 -> 11254.726 | R14: =(Q14-Q13)/Q13 -> 0.057188212
A15: Wipro | B15: FY2024 | C15: 89760 | D15: 11112 | E15: 0.19 | F15: 1045 | G15: 73488 | H15: =F15+G15 -> 74533 | I15: 16465 | J15: =I15/H15 -> 0.22090886 | K15: =D15/H15 -> 0.14908832 | L15: 0.18 | M15: 10.57 | N15: =(C15-C14)/C14 -> -0.0080452657 | O15: =D15/C15 -> 0.12379679 | P15: 82.8 | Q15: =C15*10/P15 -> 10840.58 | R15: =(Q15-Q14)/Q14 -> -0.036797577
A16: Wipro | B16: FY2025 | C16: 89088 | D16: 13218 | E16: 0.2 | F16: 2094 | G16: 80270 | H16: =F16+G16 -> 82364 | I16: 19204 | J16: =I16/H16 -> 0.23316012 | K16: =D16/H16 -> 0.16048274 | L16: 0.17 | M16: 12.54 | N16: =(C16-C15)/C15 -> -0.007486631 | O16: =D16/C16 -> 0.14837015 | P16: 84.5 | Q16: =C16*10/P16 -> 10542.959 | R16: =(Q16-Q15)/Q15 -> -0.027454356
A18: Source: screener.in (Consolidated, Rs. Crores), TCS/Infosys/Wipro FY2021-FY2025. ROE/D-E calculated from Balance Sheet. USD/INR FY-average rates are approximate (RBI Handbook of Statistics reference) - verify exact figures before final submission. USD revenue growth strips out currency effects to show real business growth vs INR-reported growth.

Sheet Charts Data
A1: Year | B1: TCS Revenue (Cr) | C1: Infosys Revenue (Cr) | D1: Wipro Revenue (Cr)
A2: FY2021 | B2: ='Financial Data'!C2 -> 164177 | C2: ='Financial Data'!C7 -> 100472 | D2: ='Financial Data'!C12 -> 61935
A3: FY2022 | B3: ='Financial Data'!C3 -> 191754 | C3: ='Financial Data'!C8 -> 121641 | D3: ='Financial Data'!C13 -> 79312
A4: FY2023 | B4: ='Financial Data'!C4 -> 225458 | C4: ='Financial Data'!C9 -> 146767 | D4: ='Financial Data'!C14 -> 90488
A5: FY2024 | B5: ='Financial Data'!C5 -> 240893 | C5: ='Financial Data'!C10 -> 153670 | D5: ='Financial Data'!C15 -> 89760
A6: FY2025 | B6: ='Financial Data'!C6 -> 255324 | C6: ='Financial Data'!C11 -> 162990 | D6: ='Financial Data'!C16 -> 89088
A23: Year | B23: TCS ROE % | C23: Infosys ROE % | D23: Wipro ROE %
A24: FY2021 | B24: ='Financial Data'!K2 -> 0.37673111 | C24: ='Financial Data'!K7 -> 0.25439091 | D24: ='Financial Data'!K12 -> 0.19795632
A25: FY2022 | B25: ='Financial Data'!K3 -> 0.43133757 | C25: ='Financial Data'!K8 -> 0.29390843 | D25: ='Financial Data'!K13 -> 0.18719325
A26: FY2023 | B26: ='Financial Data'!K4 -> 0.46782934 | C26: ='Financial Data'!K9 -> 0.31970507 | D26: ='Financial Data'!K14 -> 0.14634084
A27: FY2024 | B27: ='Financial Data'!K5 -> 0.50944314 | C27: ='Financial Data'!K10 -> 0.29788007 | D27: ='Financial Data'!K15 -> 0.14908832
A28: FY2025 | B28: ='Financial Data'!K6 -> 0.5149753 | C28: ='Financial Data'!K11 -> 0.2791751 | D28: ='Financial Data'!K16 -> 0.16048274
A38: Company | B38: Debt to Equity FY2025
A39: TCS | B39: ='Financial Data'!J6 -> 0.099117734
A40: Infosys | B40: ='Financial Data'!J11 -> 0.085860694
A41: Wipro | B41: ='Financial Data'!J16 -> 0.23316012
